datasette_sierra_ils_auth/__init__.py
datasette_sierra_ils_auth/auth_db.py
datasette_sierra_ils_auth/views.py
datasette_sierra_ils_auth/templates/sierra_auth_admin_user_edit.html
datasette_sierra_ils_auth/templates/sierra_auth_admin_users.html
datasette_sierra_ils_auth/templates/sierra_auth_error.html
datasette_sierra_ils_auth/templates/sierra_auth_login.html
datasette_sierra_ils_auth-0.1.0.dist-info/licenses/LICENSE
datasette_sierra_ils_auth-0.1.0.dist-info/METADATA
datasette_sierra_ils_auth-0.1.0.dist-info/WHEEL
datasette_sierra_ils_auth-0.1.0.dist-info/entry_points.txt
datasette_sierra_ils_auth-0.1.0.dist-info/top_level.txt
datasette_sierra_ils_auth-0.1.0.dist-info/RECORD
