Metadata-Version: 2.4
Name: datasette-sierra-ils-auth
Version: 0.1.0
Summary: Datasette plugin for authenticating staff users against Sierra ILS REST API
Author: Ray Voelker
License-Expression: MIT
Project-URL: Homepage, https://github.com/chimpy-me/datasette-sierra-ils-auth
Project-URL: Changelog, https://github.com/chimpy-me/datasette-sierra-ils-auth/releases
Project-URL: Issues, https://github.com/chimpy-me/datasette-sierra-ils-auth/issues
Project-URL: CI, https://github.com/chimpy-me/datasette-sierra-ils-auth/actions
Classifier: Framework :: Datasette
Requires-Python: >=3.10
License-File: LICENSE
Requires-Dist: datasette
Requires-Dist: sierra-ils-utils
Dynamic: license-file
